otel_observability/__init__.py
otel_observability/config.py
otel_observability/observability_manager.py
otel_observability/logs/__init__.py
otel_observability/logs/logging.py
otel_observability/metrics/__init__.py
otel_observability/metrics/metrics.py
otel_observability/traces/__init__.py
otel_observability/traces/traces.py
otel_observability-0.1.6.dist-info/licenses/LICENSE
otel_observability-0.1.6.dist-info/METADATA
otel_observability-0.1.6.dist-info/WHEEL
otel_observability-0.1.6.dist-info/top_level.txt
otel_observability-0.1.6.dist-info/RECORD
