Metadata-Version: 2.4
Name: otel-observability
Version: 0.1.6
Summary: A unified OpenTelemetry observability package for Python applications
Home-page: https://github.com/Touzi-Mortadha/otel-observability
Author: Mortada Touzi
Author-email: Mortada Touzi <mortada.touzi@gmail.com>
License: AGPL-3.0
Project-URL: Homepage, https://github.com/Touzi-Mortadha/otel-observability
Project-URL: Bug Tracker, https://github.com/Touzi-Mortadha/otel-observability/issues
Keywords: opentelemetry,observability,logging,metrics,tracing,monitoring
Classifier: Development Status :: 4 - Beta
Classifier: Intended Audience :: Developers
Classifier: License :: OSI Approved :: GNU Affero General Public License v3
Classifier: Operating System :: OS Independent
Classifier: Programming Language :: Python :: 3
Classifier: Programming Language :: Python :: 3.11
Classifier: Programming Language :: Python :: 3.12
Classifier: Programming Language :: Python :: 3.13
Classifier: Topic :: Software Development :: Libraries :: Python Modules
Classifier: Topic :: System :: Logging
Classifier: Topic :: System :: Monitoring
Requires-Python: >=3.8
License-File: LICENSE
Requires-Dist: opentelemetry-api>=1.37.0
Requires-Dist: opentelemetry-sdk>=1.37.0
Requires-Dist: opentelemetry-exporter-otlp>=1.37.0
Provides-Extra: dev
Requires-Dist: pytest>=7.0.0; extra == "dev"
Requires-Dist: pytest-cov>=4.0.0; extra == "dev"
Requires-Dist: black>=23.0.0; extra == "dev"
Requires-Dist: isort>=5.12.0; extra == "dev"
Requires-Dist: mypy>=1.0.0; extra == "dev"
Dynamic: author
Dynamic: home-page
Dynamic: license-file
Dynamic: requires-python
